pyloading_bar/__init__.py
pyloading_bar/bar.py
pyloading_bar/range_bar.py
pyloading_bar-0.0.2.dist-info/LICENSE
pyloading_bar-0.0.2.dist-info/METADATA
pyloading_bar-0.0.2.dist-info/WHEEL
pyloading_bar-0.0.2.dist-info/top_level.txt
pyloading_bar-0.0.2.dist-info/RECORD
