Metadata-Version: 2.1
Name: pyloading-bar
Version: 0.0.2
Summary: A python loading bar to use in terminal applications
Home-page: https://github.com/NalbertLeal/pyloading_bar
Author: Nalbert Gabriel Melo Leal
Author-email: nalbertgml@gmail.com
License: UNKNOWN
Project-URL: Bug Tracker, https://github.com/NalbertLeal/pyloading_bar/issues
Platform: UNKNOWN
Classifier: Programming Language :: Python :: 3
Classifier: License :: OSI Approved :: Apache Software License
Classifier: Operating System :: OS Independent
Classifier: Development Status :: 3 - Alpha
Classifier: Intended Audience :: Developers
Requires-Python: >=3.8
License-File: LICENSE
